create_package/__init__.py
create_package/calculator.py
demo_hypers-0.1.dist-info/METADATA
demo_hypers-0.1.dist-info/WHEEL
demo_hypers-0.1.dist-info/top_level.txt
demo_hypers-0.1.dist-info/RECORD
