Metadata-Version: 2.1
Name: demo-hypers
Version: 0.1
Summary: This is a library.
Home-page: 
Author: snwang
Author-email: sayneng.wang@haulio.io
Classifier: Programming Language :: Python :: 3
Classifier: License :: OSI Approved :: MIT License
Classifier: Operating System :: OS Independent
Requires-Python: >=3.7
